universalQueue/SORT.py
universalQueue/__init__.py
universalQueue-0.0.2.dist-info/LICENSE.txt
universalQueue-0.0.2.dist-info/METADATA
universalQueue-0.0.2.dist-info/WHEEL
universalQueue-0.0.2.dist-info/top_level.txt
universalQueue-0.0.2.dist-info/RECORD
