Metadata-Version: 2.1
Name: universalQueue
Version: 0.0.2
Summary: A small example package
Home-page: https://github.com/pypa/sampleproject
Author: Rifqi khairur rahman
Author-email: eaglemaster7@gmail.com
License: UNKNOWN
Platform: UNKNOWN
Classifier: Programming Language :: Python :: 3
Classifier: License :: OSI Approved :: MIT License
Classifier: Operating System :: OS Independent
